[{"url":"https://api.github.com/repos/FriendsOfREDAXO/tinymce/pulls/comments/3270299778","pull_request_review_id":4324047091,"id":3270299778,"node_id":"PRRC_kwDOCeJETc7C7NCC","diff_hunk":"@@ -8,119 +27,93 @@ const fg = require('fast-glob');\n \n const addonRoot = path.resolve(__dirname, '..');\n const customRoot = path.join(addonRoot, 'custom_plugins');\n-const destRoot = path.join(addonRoot, 'assets', 'scripts', 'tinymce', 'plugins');\n \n-function log(...args){ console.log('[build-plugins]', ...args); }\n+const args = process.argv.slice(2);\n+const staging = args.includes('--staging');\n+\n+const destRoot = staging\n+  ? path.join(addonRoot, 'build', 'plugins')\n+  : path.join(addonRoot, 'assets', 'scripts', 'tinymce', 'plugins');\n \n+function log(...a){ console.log('[build-plugins]', ...a); }\n async function ensureDir(dir){ await fsp.mkdir(dir, { recursive: true }); }\n async function removeDir(dir){ if (fs.existsSync(dir)) await fsp.rm(dir, { recursive: true, force: true }); }\n \n async function copyRecursive(src, dest){\n-  // copy everything from src into dest (dir -> dir)\n   if (!fs.existsSync(src)) return;\n   await ensureDir(dest);\n-  // prefer fs.cp if available\n   if (fsp.cp) return fsp.cp(src, dest, { recursive: true });\n   const files = await fg(['**/*'], { cwd: src, dot: true, onlyFiles: false });\n   for (const f of files){\n     const s = path.join(src, f);\n     const d = path.join(dest, f);\n     const st = await fsp.stat(s);\n-    if (st.isDirectory()){\n-      await ensureDir(d);\n-    } else {\n-      await ensureDir(path.dirname(d));\n-      await fsp.copyFile(s, d);\n-    }\n+    if (st.isDirectory()) await ensureDir(d);\n+    else { await ensureDir(path.dirname(d)); await fsp.copyFile(s, d); }\n   }\n }\n \n-const args = process.argv.slice(2);\n-const staging = args.includes('--staging');\n-\n async function buildPlugin(p){\n   const pluginDir = path.join(customRoot, p);\n   if (!fs.existsSync(pluginDir)) return;\n \n-  log('processing', p);\n-\n-  const stagingRoot = path.join(addonRoot, staging ? 'build' : 'assets');\n-  const vendorOut = path.join(stagingRoot, 'vendor', 'tinymce', 'plugins', p);\n-  const outDir = path.join(staging ? path.join(addonRoot, 'build', 'plugins') : destRoot, p);\n-\n+  const outDir = path.join(destRoot, p);\n   await removeDir(outDir);\n   await ensureDir(outDir);\n \n-  // Possible prebuilt locations to copy from\n+  // Prefer prebuilt artifacts produced by the plugin's own build script.\n   const candidates = [\n     path.join(pluginDir, 'dist', p),\n     path.join(pluginDir, 'dist'),\n     path.join(pluginDir, 'build'),\n-    path.join(pluginDir, 'lib')\n+    path.join(pluginDir, 'lib'),\n   ];\n \n   for (const c of candidates){\n     if (fs.existsSync(c)){\n-      log('copying prebuilt from', c, '->', outDir);\n+      log('copy prebuilt', path.relative(addonRoot, c), '->', path.relative(addonRoot, outDir));\n       await copyRecursive(c, outDir);\n-      // also place in vendor plugins so Tiny can load plugin via regular plugin path\n-      try{\n-        await removeDir(vendorOut);\n-        await copyRecursive(c, vendorOut);\n-        log('copied prebuilt into vendor ->', vendorOut);\n-      }catch(e){ log('failed to copy prebuilt into vendor for', p, e.message); }\n       return;\n     }\n   }\n \n-  // If no prebuilt artifact, try to bundle a common entrypoint with esbuild.\n-  // Wichtig: Main.ts kommt VOR Plugin.ts, weil Plugin.ts in der TinyMCE-Konvention\n-  // nur die Setup-Funktion exportiert (`export default (): void => {...}`), während\n-  // Main.ts diese tatsächlich aufruft (`Plugin();`). Würde esbuild Plugin.ts als\n-  // Entry nehmen, fehlt im IIFE-Output der Aufruf und das Plugin registriert sich nie.\n+  // Fallback: bundle a known entrypoint with esbuild.\n+  // Main.ts MUST come before Plugin.ts: TinyMCE convention is that Plugin.ts\n+  // only exports the setup function (`export default (): void => {...}`),\n+  // while Main.ts actually invokes it (`Plugin();`). Picking Plugin.ts as the\n+  // IIFE entry would produce a bundle that never registers itself.\n   const entryCandidates = [\n     'src/main/ts/Main.ts',\n     'src/main/ts/api/Main.ts',\n     'src/main/ts/Plugin.ts',\n     'src/main/index.ts',\n     'src/main.js',\n-    'src/index.js'\n+    'src/index.js',\n   ];\n \n   for (const rel of entryCandidates){\n     const full = path.join(pluginDir, rel);\n     if (!fs.existsSync(full)) continue;\n \n     const outfile = path.join(outDir, p + '.min.js');\n-    log('bundling', full, '->', outfile);\n+    log('bundle', path.relative(addonRoot, full), '->', path.relative(addonRoot, outfile));\n     try{","path":"scripts/build-plugins.js","commit_id":"fc4d47564bc9c936cf332d86b2aad7c40fe3f86d","original_commit_id":"22325bb70124ca98752455acacf6ca86d94ee04e","user":{"login":"Copilot","id":175728472,"node_id":"BOT_kgDOCnlnWA","avatar_url":"https://avatars.githubusercontent.com/in/946600?v=4","gravatar_id":"","url":"https://api.github.com/users/Copilot","html_url":"https://github.com/apps/copilot-pull-request-reviewer","followers_url":"https://api.github.com/users/Copilot/followers","following_url":"https://api.github.com/users/Copilot/following{/other_user}","gists_url":"https://api.github.com/users/Copilot/gists{/gist_id}","starred_url":"https://api.github.com/users/Copilot/starred{/owner}{/repo}","subscriptions_url":"https://api.github.com/users/Copilot/subscriptions","organizations_url":"https://api.github.com/users/Copilot/orgs","repos_url":"https://api.github.com/users/Copilot/repos","events_url":"https://api.github.com/users/Copilot/events{/privacy}","received_events_url":"https://api.github.com/users/Copilot/received_events","type":"Bot","user_view_type":"public","site_admin":false},"body":"In the esbuild fallback path, the bundle is written to `<outDir>/<plugin>.min.js`, but profiles/external_plugins URLs in this repo point to `<outDir>/plugin.min.js` (see assets/generated/profiles.js). If a plugin build fails or a plugin has no prebuilt dist, TinyMCE will try to load plugin.min.js and fail. Align the fallback output naming with the expected `plugin.min.js` (and, if needed, also emit an unminified `plugin.js`) or adjust the external_plugins URL generation consistently.","created_at":"2026-05-19T23:26:00Z","updated_at":"2026-05-19T23:26:01Z","html_url":"https://github.com/FriendsOfREDAXO/tinymce/pull/172#discussion_r3270299778","pull_request_url":"https://api.github.com/repos/FriendsOfREDAXO/tinymce/pulls/172","_links":{"self":{"href":"https://api.github.com/repos/FriendsOfREDAXO/tinymce/pulls/comments/3270299778"},"html":{"href":"https://github.com/FriendsOfREDAXO/tinymce/pull/172#discussion_r3270299778"},"pull_request":{"href":"https://api.github.com/repos/FriendsOfREDAXO/tinymce/pulls/172"}},"reactions":{"url":"https://api.github.com/repos/FriendsOfREDAXO/tinymce/pulls/comments/3270299778/reactions","total_count":0,"+1":0,"-1":0,"laugh":0,"hooray":0,"confused":0,"heart":0,"rocket":0,"eyes":0},"start_line":94,"original_start_line":94,"start_side":"RIGHT","line":103,"original_line":100,"side":"RIGHT","author_association":"CONTRIBUTOR","original_position":133,"position":137,"subject_type":"line"},{"url":"https://api.github.com/repos/FriendsOfREDAXO/tinymce/pulls/comments/3270299793","pull_request_review_id":4324047091,"id":3270299793,"node_id":"PRRC_kwDOCeJETc7C7NCR","diff_hunk":"@@ -1162,106 +1129,13 @@ const setup = (editor: Editor, _url: string): void => {\n         return;\n       }\n \n-      if (typeof openREXMedia !== 'function') {\n-        editor.notificationManager.open({ \n-          text: 'Medienpool ist nicht verfügbar.', \n-          type: 'error', \n-          timeout: 3000 \n-        });\n-        return;\n-      }\n-\n+      // Ensure the selection is on the IMG (not the wrapping FIGURE/FIGCAPTION)\n+      // so the standard image dialog picks it up as \"edit existing image\".\n       try {\n-        const mediaPool = openREXMedia('tinymce_medialink', '&args[types]=jpg%2Cjpeg%2Cpng%2Cgif%2Cbmp%2Ctiff%2Csvg%2Cwebp');\n-\n-        // Use jQuery to listen for media selection if available\n-        if (typeof $ !== 'undefined' && $ && typeof $.fn.on === 'function') {\n-          $(mediaPool).on('rex:selectMedia', function (event: any, filename: string) {\n-            event.preventDefault();\n-            mediaPool.close();\n-\n-            // Determine the correct path based on file extension\n-            const extension = filename.split('.').pop()?.toLowerCase() || '';\n-            const useMediaManager = ['jpg', 'jpeg', 'png', 'gif', 'webp'].indexOf(extension) !== -1;\n-            const imagePath = useMediaManager ? '/media/tiny/' + filename : '/media/' + filename;\n-\n-            // Get current config to know which classes to remove\n-            const config = configCache.get();\n-            const figure = getFigureWrap(img);\n-            \n-            // Remove all preset classes (width, align, effects) to reset to original\n-            if (figure) {\n-              stripPresetClasses(figure, config.widthPresets);\n-              stripPresetClasses(figure, config.alignPresets);\n-              stripPresetClasses(figure, config.effectPresets);\n-              // Also remove any legacy CKE5 classes\n-              stripCke5LegacyClasses(figure);\n-              // Remove all attributes/styles\n-              if (figure.classList.length === 0) figure.removeAttribute('class');\n-            }\n-            \n-            // Remove old inline dimensions from img\n-            img.removeAttribute('width');\n-            img.removeAttribute('height');\n-            img.style.removeProperty('width');\n-            img.style.removeProperty('height');\n-            if (img.getAttribute('style') === '') img.removeAttribute('style');\n-            \n-            // Update the image src with new image\n-            img.setAttribute('src', imagePath);\n-            \n-            // Wait for image to load, then update editor\n-            const onImageLoad = () => {\n-              img.removeEventListener('load', onImageLoad);\n-              img.removeEventListener('error', onImageError);\n-              editor.nodeChanged();\n-              editor.undoManager.add();\n-            };\n-            \n-            const onImageError = () => {\n-              img.removeEventListener('load', onImageLoad);\n-              img.removeEventListener('error', onImageError);\n-              editor.nodeChanged();\n-              editor.undoManager.add();\n-            };\n-            \n-            img.addEventListener('load', onImageLoad);\n-            img.addEventListener('error', onImageError);\n-            \n-            // Try to fetch media metadata (alt text, etc.)\n-            if (typeof $ !== 'undefined' && $.getJSON) {\n-              $.getJSON(\n-                'index.php?rex-api-call=tinymce_media_meta&file=' + encodeURIComponent(filename)\n-              ).done(function (meta: any) {\n-                if (meta && meta.alt) {\n-                  img.setAttribute('alt', meta.alt);\n-                }\n-              }).fail(function () {\n-                // If metadata fetch fails, just keep existing alt or leave empty\n-              });\n-            }\n-            \n-            editor.notificationManager.open({\n-              text: `Bild erfolgreich aktualisiert: ${filename}`,\n-              type: 'success',\n-              timeout: 3000\n-            });\n-          });\n-        } else {\n-          // Fallback if jQuery is not available\n-          editor.notificationManager.open({ \n-            text: 'jQuery ist nicht verfügbar. Bitte verwenden Sie den Standard-Medienpool.', \n-            type: 'warning', \n-            timeout: 5000 \n-          });\n-        }\n-      } catch (e) {\n-        editor.notificationManager.open({ \n-          text: 'Medienpool konnte nicht geöffnet werden.', \n-          type: 'error', \n-          timeout: 3000 \n-        });\n-      }\n+        editor.selection.select(img);\n+      } catch (e) { /* ignore */ }\n+\n+      editor.execCommand('mceImage');\n     }","path":"custom_plugins/for_images/src/main/ts/Plugin.ts","commit_id":"fc4d47564bc9c936cf332d86b2aad7c40fe3f86d","original_commit_id":"22325bb70124ca98752455acacf6ca86d94ee04e","user":{"login":"Copilot","id":175728472,"node_id":"BOT_kgDOCnlnWA","avatar_url":"https://avatars.githubusercontent.com/in/946600?v=4","gravatar_id":"","url":"https://api.github.com/users/Copilot","html_url":"https://github.com/apps/copilot-pull-request-reviewer","followers_url":"https://api.github.com/users/Copilot/followers","following_url":"https://api.github.com/users/Copilot/following{/other_user}","gists_url":"https://api.github.com/users/Copilot/gists{/gist_id}","starred_url":"https://api.github.com/users/Copilot/starred{/owner}{/repo}","subscriptions_url":"https://api.github.com/users/Copilot/subscriptions","organizations_url":"https://api.github.com/users/Copilot/orgs","repos_url":"https://api.github.com/users/Copilot/repos","events_url":"https://api.github.com/users/Copilot/events{/privacy}","received_events_url":"https://api.github.com/users/Copilot/received_events","type":"Bot","user_view_type":"public","site_admin":false},"body":"`imageswappool` delegates to `editor.execCommand('mceImage')`, but that command is only available when TinyMCE's built-in `image` plugin is enabled. Since profiles can toggle plugins independently, this button can become a no-op (or error) if `image` is disabled while `for_images` is enabled. Consider guarding via `editor.queryCommandSupported('mceImage')`/`editor.plugins.image` and showing a clear notification when the image dialog isn't available.","created_at":"2026-05-19T23:26:01Z","updated_at":"2026-05-19T23:26:01Z","html_url":"https://github.com/FriendsOfREDAXO/tinymce/pull/172#discussion_r3270299793","pull_request_url":"https://api.github.com/repos/FriendsOfREDAXO/tinymce/pulls/172","_links":{"self":{"href":"https://api.github.com/repos/FriendsOfREDAXO/tinymce/pulls/comments/3270299793"},"html":{"href":"https://github.com/FriendsOfREDAXO/tinymce/pull/172#discussion_r3270299793"},"pull_request":{"href":"https://api.github.com/repos/FriendsOfREDAXO/tinymce/pulls/172"}},"reactions":{"url":"https://api.github.com/repos/FriendsOfREDAXO/tinymce/pulls/comments/3270299793/reactions","total_count":0,"+1":0,"-1":0,"laugh":0,"hooray":0,"confused":0,"heart":0,"rocket":0,"eyes":0},"start_line":1122,"original_start_line":1122,"start_side":"RIGHT","line":1156,"original_line":1139,"side":"RIGHT","author_association":"CONTRIBUTOR","original_position":368,"position":382,"subject_type":"line"},{"url":"https://api.github.com/repos/FriendsOfREDAXO/tinymce/pulls/comments/3270299802","pull_request_review_id":4324047091,"id":3270299802,"node_id":"PRRC_kwDOCeJETc7C7NCa","diff_hunk":"@@ -8,119 +27,93 @@ const fg = require('fast-glob');\n \n const addonRoot = path.resolve(__dirname, '..');\n const customRoot = path.join(addonRoot, 'custom_plugins');\n-const destRoot = path.join(addonRoot, 'assets', 'scripts', 'tinymce', 'plugins');\n \n-function log(...args){ console.log('[build-plugins]', ...args); }\n+const args = process.argv.slice(2);\n+const staging = args.includes('--staging');\n+\n+const destRoot = staging\n+  ? path.join(addonRoot, 'build', 'plugins')\n+  : path.join(addonRoot, 'assets', 'scripts', 'tinymce', 'plugins');\n \n+function log(...a){ console.log('[build-plugins]', ...a); }\n async function ensureDir(dir){ await fsp.mkdir(dir, { recursive: true }); }\n async function removeDir(dir){ if (fs.existsSync(dir)) await fsp.rm(dir, { recursive: true, force: true }); }\n \n async function copyRecursive(src, dest){\n-  // copy everything from src into dest (dir -> dir)\n   if (!fs.existsSync(src)) return;\n   await ensureDir(dest);\n-  // prefer fs.cp if available\n   if (fsp.cp) return fsp.cp(src, dest, { recursive: true });\n   const files = await fg(['**/*'], { cwd: src, dot: true, onlyFiles: false });\n   for (const f of files){\n     const s = path.join(src, f);\n     const d = path.join(dest, f);\n     const st = await fsp.stat(s);\n-    if (st.isDirectory()){\n-      await ensureDir(d);\n-    } else {\n-      await ensureDir(path.dirname(d));\n-      await fsp.copyFile(s, d);\n-    }\n+    if (st.isDirectory()) await ensureDir(d);\n+    else { await ensureDir(path.dirname(d)); await fsp.copyFile(s, d); }\n   }\n }\n \n-const args = process.argv.slice(2);\n-const staging = args.includes('--staging');\n-\n async function buildPlugin(p){\n   const pluginDir = path.join(customRoot, p);\n   if (!fs.existsSync(pluginDir)) return;\n \n-  log('processing', p);\n-\n-  const stagingRoot = path.join(addonRoot, staging ? 'build' : 'assets');\n-  const vendorOut = path.join(stagingRoot, 'vendor', 'tinymce', 'plugins', p);\n-  const outDir = path.join(staging ? path.join(addonRoot, 'build', 'plugins') : destRoot, p);\n-\n+  const outDir = path.join(destRoot, p);\n   await removeDir(outDir);\n   await ensureDir(outDir);\n \n-  // Possible prebuilt locations to copy from\n+  // Prefer prebuilt artifacts produced by the plugin's own build script.\n   const candidates = [\n     path.join(pluginDir, 'dist', p),\n     path.join(pluginDir, 'dist'),\n     path.join(pluginDir, 'build'),\n-    path.join(pluginDir, 'lib')\n+    path.join(pluginDir, 'lib'),\n   ];\n \n   for (const c of candidates){\n     if (fs.existsSync(c)){\n-      log('copying prebuilt from', c, '->', outDir);\n+      log('copy prebuilt', path.relative(addonRoot, c), '->', path.relative(addonRoot, outDir));\n       await copyRecursive(c, outDir);\n-      // also place in vendor plugins so Tiny can load plugin via regular plugin path\n-      try{\n-        await removeDir(vendorOut);\n-        await copyRecursive(c, vendorOut);\n-        log('copied prebuilt into vendor ->', vendorOut);\n-      }catch(e){ log('failed to copy prebuilt into vendor for', p, e.message); }\n       return;\n     }\n   }\n \n-  // If no prebuilt artifact, try to bundle a common entrypoint with esbuild.\n-  // Wichtig: Main.ts kommt VOR Plugin.ts, weil Plugin.ts in der TinyMCE-Konvention\n-  // nur die Setup-Funktion exportiert (`export default (): void => {...}`), während\n-  // Main.ts diese tatsächlich aufruft (`Plugin();`). Würde esbuild Plugin.ts als\n-  // Entry nehmen, fehlt im IIFE-Output der Aufruf und das Plugin registriert sich nie.\n+  // Fallback: bundle a known entrypoint with esbuild.\n+  // Main.ts MUST come before Plugin.ts: TinyMCE convention is that Plugin.ts\n+  // only exports the setup function (`export default (): void => {...}`),\n+  // while Main.ts actually invokes it (`Plugin();`). Picking Plugin.ts as the\n+  // IIFE entry would produce a bundle that never registers itself.\n   const entryCandidates = [\n     'src/main/ts/Main.ts',\n     'src/main/ts/api/Main.ts',\n     'src/main/ts/Plugin.ts',\n     'src/main/index.ts',\n     'src/main.js',\n-    'src/index.js'\n+    'src/index.js',\n   ];\n \n   for (const rel of entryCandidates){\n     const full = path.join(pluginDir, rel);\n     if (!fs.existsSync(full)) continue;\n \n     const outfile = path.join(outDir, p + '.min.js');\n-    log('bundling', full, '->', outfile);\n+    log('bundle', path.relative(addonRoot, full), '->', path.relative(addonRoot, outfile));\n     try{\n       await esbuild.build({\n         entryPoints: [full],\n         bundle: true,\n         minify: true,\n         format: 'iife',\n         target: ['es2017'],\n-        outfile: outfile,\n-        sourcemap: false\n+        outfile,\n+        sourcemap: false,\n       });","path":"scripts/build-plugins.js","commit_id":"fc4d47564bc9c936cf332d86b2aad7c40fe3f86d","original_commit_id":"22325bb70124ca98752455acacf6ca86d94ee04e","user":{"login":"Copilot","id":175728472,"node_id":"BOT_kgDOCnlnWA","avatar_url":"https://avatars.githubusercontent.com/in/946600?v=4","gravatar_id":"","url":"https://api.github.com/users/Copilot","html_url":"https://github.com/apps/copilot-pull-request-reviewer","followers_url":"https://api.github.com/users/Copilot/followers","following_url":"https://api.github.com/users/Copilot/following{/other_user}","gists_url":"https://api.github.com/users/Copilot/gists{/gist_id}","starred_url":"https://api.github.com/users/Copilot/starred{/owner}{/repo}","subscriptions_url":"https://api.github.com/users/Copilot/subscriptions","organizations_url":"https://api.github.com/users/Copilot/orgs","repos_url":"https://api.github.com/users/Copilot/repos","events_url":"https://api.github.com/users/Copilot/events{/privacy}","received_events_url":"https://api.github.com/users/Copilot/received_events","type":"Bot","user_view_type":"public","site_admin":false},"body":"The esbuild fallback bundles without `external: ['tinymce']`. Since plugin sources import from `tinymce`, this fallback will likely inline the entire TinyMCE package into each plugin bundle (large output and potential runtime duplication), whereas the per-plugin build scripts externalize tinymce. Add `external: ['tinymce']` (and keep the global `tinymce` runtime dependency) to make the fallback behave consistently with the normal plugin builds.","created_at":"2026-05-19T23:26:01Z","updated_at":"2026-05-19T23:26:01Z","html_url":"https://github.com/FriendsOfREDAXO/tinymce/pull/172#discussion_r3270299802","pull_request_url":"https://api.github.com/repos/FriendsOfREDAXO/tinymce/pulls/172","_links":{"self":{"href":"https://api.github.com/repos/FriendsOfREDAXO/tinymce/pulls/comments/3270299802"},"html":{"href":"https://github.com/FriendsOfREDAXO/tinymce/pull/172#discussion_r3270299802"},"pull_request":{"href":"https://api.github.com/repos/FriendsOfREDAXO/tinymce/pulls/172"}},"reactions":{"url":"https://api.github.com/repos/FriendsOfREDAXO/tinymce/pulls/comments/3270299802/reactions","total_count":0,"+1":0,"-1":0,"laugh":0,"hooray":0,"confused":0,"heart":0,"rocket":0,"eyes":0},"start_line":103,"original_start_line":100,"start_side":"RIGHT","line":116,"original_line":109,"side":"RIGHT","author_association":"CONTRIBUTOR","original_position":144,"position":152,"subject_type":"line"},{"url":"https://api.github.com/repos/FriendsOfREDAXO/tinymce/pulls/comments/3270384105","pull_request_review_id":4324149014,"id":3270384105,"node_id":"PRRC_kwDOCeJETc7C7hnp","diff_hunk":"@@ -149,24 +151,26 @@ async function main(){\n   const plugins = items.filter(i => i.isDirectory()).map(i => i.name);\n \n   for (const p of plugins){\n+    log('processing', p);\n     const pluginDir = path.join(customRoot, p);\n     const packageJson = path.join(pluginDir, 'package.json');\n \n     if (fs.existsSync(packageJson)){\n       try{\n         const pkg = JSON.parse(await fsp.readFile(packageJson, 'utf8'));\n         if (pkg.scripts && pkg.scripts.build){\n-          log('running build script for', p);\n-          try{ execSync('pnpm run build', { stdio: 'inherit', cwd: pluginDir }); }\n-          catch(e){ log('plugin build failed for', p, '- continuing (error ignored)'); }\n+          log('  run plugin build script');\n+          try { execSync('pnpm run build', { stdio: 'inherit', cwd: pluginDir }); }\n+          catch (e) { log('  plugin build failed for', p, '- continuing (error ignored)'); }\n         }","path":"scripts/build-plugins.js","commit_id":"fc4d47564bc9c936cf332d86b2aad7c40fe3f86d","original_commit_id":"fc4d47564bc9c936cf332d86b2aad7c40fe3f86d","user":{"login":"Copilot","id":175728472,"node_id":"BOT_kgDOCnlnWA","avatar_url":"https://avatars.githubusercontent.com/in/946600?v=4","gravatar_id":"","url":"https://api.github.com/users/Copilot","html_url":"https://github.com/apps/copilot-pull-request-reviewer","followers_url":"https://api.github.com/users/Copilot/followers","following_url":"https://api.github.com/users/Copilot/following{/other_user}","gists_url":"https://api.github.com/users/Copilot/gists{/gist_id}","starred_url":"https://api.github.com/users/Copilot/starred{/owner}{/repo}","subscriptions_url":"https://api.github.com/users/Copilot/subscriptions","organizations_url":"https://api.github.com/users/Copilot/orgs","repos_url":"https://api.github.com/users/Copilot/repos","events_url":"https://api.github.com/users/Copilot/events{/privacy}","received_events_url":"https://api.github.com/users/Copilot/received_events","type":"Bot","user_view_type":"public","site_admin":false},"body":"When running with `--staging`, this script still executes each plugin’s `pnpm run build` (which typically runs `build-copy` and writes directly into `assets/scripts/...`). That undermines the purpose of a staging build (`build/` should be the only output of `build:staging`) and can leave the working tree dirty or with stale files if `build-copy` doesn’t fully overwrite/remove previous outputs. Consider skipping plugin `build-copy` in staging mode (e.g. run only the build step that produces `dist/`, or pass an env/flag that makes plugin builds write into `build/plugins/` instead of `assets/`).","created_at":"2026-05-19T23:52:07Z","updated_at":"2026-05-19T23:52:08Z","html_url":"https://github.com/FriendsOfREDAXO/tinymce/pull/172#discussion_r3270384105","pull_request_url":"https://api.github.com/repos/FriendsOfREDAXO/tinymce/pulls/172","_links":{"self":{"href":"https://api.github.com/repos/FriendsOfREDAXO/tinymce/pulls/comments/3270384105"},"html":{"href":"https://github.com/FriendsOfREDAXO/tinymce/pull/172#discussion_r3270384105"},"pull_request":{"href":"https://api.github.com/repos/FriendsOfREDAXO/tinymce/pulls/172"}},"reactions":{"url":"https://api.github.com/repos/FriendsOfREDAXO/tinymce/pulls/comments/3270384105/reactions","total_count":0,"+1":0,"-1":0,"laugh":0,"hooray":0,"confused":0,"heart":0,"rocket":0,"eyes":0},"start_line":158,"original_start_line":158,"start_side":"RIGHT","line":165,"original_line":165,"side":"RIGHT","author_association":"CONTRIBUTOR","original_position":218,"position":218,"subject_type":"line"}]